Workbook

Sheet Politicas
D6: Vigencia desde y hasta: | E6: 45608 | F6: 45623
A7: AFILIADOS | B7: Catálogo Noviembre | C7: tipo de oferta | D7: publicación | E7: Medio Pago | F7: ES precio oferta? | G7: Es tasa peque? | H7: Es sin interes? | I7: Adicional AFILIADOS 5% revista | J7: + Tiempo, + Beneficio | K7: Adicional % contado
C8: sin interés | D8: 3 sin interés | E8: TARJETA BANCARIAS EN CUOTAS- NARANJA- TUYA-PROGRAMA AHORA MISIONES- | F8: SI | G8: SI | H8: SI | I8: SI | J8: NO | K8: NO
C9: sin interés | D9: 6 a 12 sin interés | E9: TARJETA BANCARIAS EN CUOTAS- NARANJA- TUYA-PROGRAMA AHORA MISIONES- | F9: SI | G9: SI | H9: SI | I9: =+I8 -> SI | J9: NO | K9: NO
C10: sin interés | D10: 6 a 12 sin interés | E10: EFECTIVO-DEBITO- TRANSFERENCIA - CUENTA CORRIENTE | F10: SI | G10: SI | H10: SI | I10: =+I8 -> SI | J10: NO | K10: SI
C11: Peque tasa | D11: de 10 a 24 cuotas | E11: TARJETA BANCARIAS, NARANJA , TUYA | F11: SI | G11: SI | H11: SI | I11: =+I10 -> SI | J11: NO | K11: SI
C12: contado / con interés | D12: todas | E12: TARJETAS NO BANCARIAS EN CUOTAS - NARANJA- TUYA - SIDECREER - LOCRED- FINACIERAS- MERCADO PAGO- CUENTA CORRIENTE 2 A 12- | F12: SI | G12: NO | H12: NO | I12: =+I11 -> SI | J12: NO | K12: NO
C13: contado / con interés | D13: todas | E13: EFECTIVO-DEBITO- TRANSFERENCIA -CUENTA CORRIENTE | F13: SI | G13: NO | H13: NO | I13: =+I12 -> SI | J13: NO | K13: NO
A16: CONSUMIDOR FINAL | B16: =+B7 -> Catálogo Noviembre | C16: tipo de oferta | D16: publicación | E16: Medio Pago | F16: ES precio oferta? | G16: Es tasa peque? | H16: Es sin interes? | I16: =+I7 -> Adicional AFILIADOS 5% revista | J16: + Tiempo, + Beneficio | K16: =+K7 -> Adicional % contado
C17: sin interés | D17: 3 sin interés | E17: TARJETA BANCARIAS EN CUOTAS- NARANJA- TUYA-PROGRAMA AHORA MISIONES- | F17: SI | G17: SI | H17: SI | I17: NO | J17: NO | K17: NO
C18: sin interés | D18: 6 a 12 sin interés | E18: TARJETA BANCARIAS EN CUOTAS- NARANJA- TUYA-PROGRAMA AHORA MISIONES- | F18: SI | G18: SI | H18: SI | I18: =+I17 -> NO | J18: NO | K18: NO
C19: sin interés | D19: 6 a 12 sin interés | E19: EFECTIVO-DEBITO- TRANSFERENCIA -FINANCIACIÓN 1 PAGO TARJETA CREDITO- CUENTA CORRIENTE | F19: SI | G19: SI | H19: SI | I19: =+I18 -> NO | J19: NO | K19: SI (con Gtia o Blister)
C20: Peque tasa | D20: de 10 a 24 cuotas | E20: TARJETA BANCARIAS, NARANJA , TUYA | F20: SI | G20: SI | H20: SI | I20: =+I19 -> NO | J20: NO | K20: SI (con Gtia o Blister)
C21: contado / con interés | D21: todas | E21: TARJETAS NO BANCARIAS EN CUOTAS - NARANJA- TUYA - SIDECREER - LOCRED- FINACIERAS- MERCADO PAGO- CUENTA CORRIENTE 2 A 12- | F21: SI | G21: NO | H21: NO | I21: =+I20 -> NO | J21: NO | K21: NO
C22: contado / con interés | D22: todas | E22: EFECTIVO-DEBITO- TRANSFERENCIA -FINANCIACIÓN 1 PAGO TARJETA CREDITO- CUENTA CORRIENTE | F22: SI | G22: NO | H22: NO | I22: =+I21 -> NO | J22: NO | K22: NO

Sheet convinaciones fina
A1: Tipo Cuota Simple | B1: Naranja | C1: Peque | D1: Medio Cuota Simple | E1: Medio pago Naranja | F1: Medio Pago TUYA | G1: Medio Pago Sidecreer | H1: Medio Pago Consumax | I1: Medio Pago Directo CP | J1: Contado | K1: Bco Nación, BBVA, Galicia, Macro
A2: ----- | B2: Peque 10 | C2: hasta 10 cuotas | D2: hasta 6 cuotas | E2: hasta 3 cuotas | F2: hasta 3 cuotas por Peque consultar | G2: hasta 3 cuotas | H2: Plan Max | I2: hasta 15 cuotas "con interés" | J2: 0
A3: Peque 12 | B3: Peque 12 | C3: hasta 12 cuotas | D3: hasta 6 cuotas | E3: hasta 6 cuotas | F3: hasta 3 cuotas por Peque consultar | G3: hasta 3 cuotas | H3: Plan Max | I3: hasta 15 cuotas "con interés" | J3: 20
A4: Peque 18 | B4: Peque 18 | C4: hasta 18 cuotas | D4: hasta 6 cuotas | E4: hasta 6 cuotas | F4: hasta 3 cuotas por Peque consultar | G4: hasta 3 cuotas | H4: Plan Max | I4: hasta 15 cuotas "con interés" | J4: 10
A5: Peque 24 | B5: Peque 24 | C5: hasta 24 cuotas | D5: hasta 6 cuotas | E5: hasta 6 cuotas | F5: hasta 3 cuotas por Peque consultar | G5: hasta 3 cuotas | H5: Plan Max | I5: hasta 15 cuotas "con interés" | J5: 10
A6: Sin Int 3 | B6: Sin Int 3 | C6: NO Tiene habilitado | D6: hasta 3 cuotas | E6: hasta 3 cuotas | F6: hasta 1 pago | G6: NO Tiene habilitado | H6: NO Tiene habilitado | I6: hasta 15 cuotas "con interés" | J6: 0 | K6: hasta 1 cuotas
A7: Sin Int 6 | B7: Sin Int 6 | C7: hasta 12 cuotas | D7: hasta 6 cuotas | E7: hasta 6 cuotas | F7: hasta 3 cuotas | G7: hasta 3 cuotas | H7: Plan Max | I7: hasta 15 cuotas "con interés" | J7: 10 | K7: hasta 3 cuotas
A8: ----- | B8: Sin Int 10 | C8: hasta 12 cuotas | D8: hasta 12 cuotas | E8: hasta 10 cuotas | F8: hasta 5 cuotas | G8: hasta 6 cuotas | H8: hasta 6 cuotas | I8: hasta 4 cuotas "Sin interés" | J8: 0 | K8: hasta 6 cuotas
A9: Sin Int 12 | B9: Sin Int 6 | C9: hasta 18 cuotas | D9: hasta 12 cuotas | E9: hasta 6 cuotas | F9: hasta 3 cuotas | G9: hasta 3 cuotas | H9: Plan Max | I9: hasta 15 cuotas "con interés" | J9: 10 | K9: hasta 3 cuotas
A10: Sin Int 18 | B10: Sin Int 12 | C10: hasta 18 cuotas | D10: hasta 18 cuotas | E10: hasta 12 cuotas | F10: hasta 6 cuotas | G10: hasta 6 cuotas | H10: hasta 6 cuotas | I10: hasta 4 cuotas "Sin interés" | J10: 20 | K10: hasta 6 cuotas
A11: Sin Int 9 | B11: Sin Int 6 | C11: hasta 10 cuotas | D11: hasta 9 cuotas | E11: hasta 6 cuotas | F11: hasta 3 cuotas | G11: hasta 3 cuotas | H11: Plan Max | I11: hasta 15 cuotas "con interés" | J11: 10 | K11: hasta 4 cuotas
A12: Sin Int 10 | B12: Sin Int 10 | C12: hasta 12 cuotas | D12: hasta 10 cuotas | E12: hasta 10 cuotas | F12: hasta 5 cuotas | G12: hasta 6 cuotas | I12: hasta 4 cuotas "Sin interés" | K12: hasta 6 cuotas
A13: Sin Int 6 | B13: Sin Int 9 | C13: hasta 12 cuotas | D13: hasta 9 cuotas | E13: hasta 9 cuotas | F13: hasta 5 cuotas | G13: hasta 3 cuotas | H13: hasta 6 cuotas | I13: hasta 4 cuotas "Sin interés" | J13: 10 | K13: hasta 6 cuotas
A14: Sin Int 12 | B14: Sin Int 18 | C14: hasta 18 cuotas | D14: Sin Int 12 | E14: hasta 18 cuotas | F14: hasta 5 cuotas | G14: hasta 3 cuotas | H14: hasta 6 cuotas | I14: hasta 4 cuotas "Sin interés" | J14: 30 | K14: hasta 10 cuotas
A15: Oferta Cont 1 | B15: Oferta Cont 1 | C15: NO Tiene habilitado | D15: NO Tiene habilitado | E15: NO Tiene habilitado | F15: NO Tiene habilitado | G15: NO Tiene habilitado | H15: NO Tiene habilitado | I15: hasta 15 cuotas "con interés" | J15: 0 | K15: hasta 1 cuotas

Sheet Hoja1

Sheet Productos
A1: SKU | B1: Articulo | C1: Marca | D1: Rubro | E1: Precio Vta P | F1: Ahorro | G1: Precio Oferta | H1: En Catalogo | I1: Afil Desc | J1: Desc Contado | K1: Tipo Fciación | L1: Cuotas: | M1: CUOTAS.A | N1: Importe Cuota A | O1: _ | P1: CFT | Q1: PTF | R1: Tasa Naranja | S1: CUOTAS.N | T1: Importe Cuota N | U1: CUOTAS.T | V1: Importe Cuota T | W1: __ | X1: CFT_1 | Y1: PTF_1 | Z1: Cod Art | AA1: Venta Tarjeta Cuotas | AB1: Cod Posnet | AC1: MP Softland | AD1: FechaInicio | AE1: FechaFin | AF1: ST | AG1: Para Web
A2: 1002631 | B2: Notebook 14,1" HD Celeron N4020 4GB SSD 128GB Windows 11 - PCBOX (PCB-GLW4EE) | C2: PCBOX | D2: 103632.18 | E2: 518156.18 | F2: 20.000182 | G2: 414524 | H2: Promo TV mundial | I2: 0.05 | J2: 0.15 | K2: Sin Int | L2: 12 | M2: 12 cuotas | N2: =+$G2/12 -> 34543.667 | O2: 0 | P2: 0 | Q2: =+N2 -> 34543.667 | R2: Sin Int | S2: 12 | T2: =+$G2/12 -> 34543.667 | U2: 9 | V2: =+G2/9 -> 46058.222 | X2: 0 | Y2: =+G2 -> 414524 | Z2: =+A2 -> 1002631 | AA2: 12 | AB2: 12 | AC2: Promo electro cuota sin interes Bancarias (todo en PAYWAY Si es cabal cód 12) | AD2: 46170 | AE2: 46203 | AF2: 0 | AG2: 12Sin IntBancarias+12Sin IntNaranja+9Tuya
A3: 1003204 | B3: Notebook Ryzen 3 8GB SSD 256GB 15,6" Windows 11 Pantalla IPS - PCBOX (78601) | C3: PCBOX | D3: 258650.69 | E3: 1293250.7 | F3: 20.000043 | G3: 1034600 | H3: Promo TV mundial | I3: 0.05 | J3: 0.15 | K3: Sin Int | L3: 12 | M3: 12 cuotas | N3: =+$G3/12 -> 86216.667 | O3: 0 | P3: 0 | Q3: =+N3 -> 86216.667 | R3: Sin Int | S3: 12 | T3: =+$G3/12 -> 86216.667 | U3: 9 | V3: =+G3/9 -> 114955.56 | X3: 0 | Y3: =+G3 -> 1034600 | Z3: =+A3 -> 1003204 | AA3: 12 | AB3: 12 | AC3: Promo electro cuota sin interes Bancarias (todo en PAYWAY Si es cabal cód 12) | AD3: 46170 | AE3: 46203 | AF3: 0 | AG3: 12Sin IntBancarias+12Sin IntNaranja+9Tuya
A4: 1002993 | B4: Smart TV 32" HD Android TV - PHILCO (PLD32HS25AH) | C4: PHILCO | D4: 89152 | E4: 445760 | F4: 20 | G4: 356608 | H4: Promo TV mundial | I4: 0.05 | J4: 0.15 | K4: Sin Int | L4: 12 | M4: 12 cuotas | N4: =+$G4/12 -> 29717.333 | O4: 0 | P4: 0 | Q4: =+N4 -> 29717.333 | R4: Sin Int | S4: 12 | T4: =+$G4/12 -> 29717.333 | U4: 9 | V4: =+G4/9 -> 39623.111 | X4: 0 | Y4: =+G4 -> 356608 | Z4: =+A4 -> 1002993 | AA4: 12 | AB4: 12 | AC4: Promo electro cuota sin interes Bancarias (todo en PAYWAY Si es cabal cód 12) | AD4: 46170 | AE4: 46203 | AF4: 0 | AG4: 12Sin IntBancarias+12Sin IntNaranja+9Tuya
A5: 1003028 | B5: Smart TV 32" HD Google TV - BGH (B3226G5G) | C5: BGH | D5: 80794 | E5: 403970 | F5: 20 | G5: 323176 | H5: Promo TV mundial | I5: 0.05 | J5: 0.15 | K5: Sin Int | L5: 12 | M5: 12 cuotas | N5: =+$G5/12 -> 26931.333 | O5: 0 | P5: 0 | Q5: =+N5 -> 26931.333 | R5: Sin Int | S5: 12 | T5: =+$G5/12 -> 26931.333 | U5: 9 | V5: =+G5/9 -> 35908.444 | X5: 0 | Y5: =+G5 -> 323176 | Z5: =+A5 -> 1003028 | AA5: 12 | AB5: 12 | AC5: Promo electro cuota sin interes Bancarias (todo en PAYWAY Si es cabal cód 12) | AD5: 46170 | AE5: 46203 | AF5: 0 | AG5: 12Sin IntBancarias+12Sin IntNaranja+9Tuya
A6: 1002992 | B6: Smart TV 32" HD Roku TV - NOBLEX (DB32X3010) | C6: NOBLEX | D6: 89152 | E6: 445760 | F6: 20 | G6: 356608 | H6: Promo TV mundial | I6: 0.05 | J6: 0.15 | K6: Sin Int | L6: 12 | M6: 12 cuotas | N6: =+$G6/12 -> 29717.333 | O6: 0 | P6: 0 | Q6: =+N6 -> 29717.333 | R6: Sin Int | S6: 12 | T6: =+$G6/12 -> 29717.333 | U6: 9 | V6: =+G6/9 -> 39623.111 | X6: 0 | Y6: =+G6 -> 356608 | Z6: =+A6 -> 1002992 | AA6: 12 | AB6: 12 | AC6: Promo electro cuota sin interes Bancarias (todo en PAYWAY Si es cabal cód 12) | AD6: 46170 | AE6: 46203 | AF6: 0 | AG6: 12Sin IntBancarias+12Sin IntNaranja+9Tuya
A7: 1000844 | B7: Smart TV 32" HD Titan OS - PHILIPS (32PHD6910/77) | C7: PHILIPS | D7: 88957.9 | E7: 444784.9 | F7: 20.000207 | G7: 355827 | H7: Promo TV mundial | I7: 0.05 | J7: 0.15 | K7: Sin Int | L7: 12 | M7: 12 cuotas | N7: =+$G7/12 -> 29652.25 | O7: 0 | P7: 0 | Q7: =+N7 -> 29652.25 | R7: Sin Int | S7: 12 | T7: =+$G7/12 -> 29652.25 | U7: 9 | V7: =+G7/9 -> 39536.333 | X7: 0 | Y7: =+G7 -> 355827 | Z7: =+A7 -> 1000844 | AA7: 12 | AB7: 12 | AC7: Promo electro cuota sin interes Bancarias (todo en PAYWAY Si es cabal cód 12) | AD7: 46170 | AE7: 46203 | AF7: 0 | AG7: 12Sin IntBancarias+12Sin IntNaranja+9Tuya
A8: 1002552 | B8: Smart TV 32" HD Titan OS - PHILIPS (32PHD6929/77) | C8: PHILIPS | D8: 75620 | E8: 378100 | F8: 20 | G8: 302480 | H8: Promo TV mundial | I8: 0.05 | J8: 0.15 | K8: Sin Int | L8: 12 | M8: 12 cuotas | N8: =+$G8/12 -> 25206.667 | O8: 0 | P8: 0 | Q8: =+N8 -> 25206.667 | R8: Sin Int | S8: 12 | T8: =+$G8/12 -> 25206.667 | U8: 9 | V8: =+G8/9 -> 33608.889 | X8: 0 | Y8: =+G8 -> 302480 | Z8: =+A8 -> 1002552 | AA8: 12 | AB8: 12 | AC8: Promo electro cuota sin interes Bancarias (todo en PAYWAY Si es cabal cód 12) | AD8: 46170 | AE8: 46203 | AF8: 0 | AG8: 12Sin IntBancarias+12Sin IntNaranja+9Tuya
A9: 1002997 | B9: Smart TV 50" UHD 4K QLED Black Series Google TV - NOBLEX (DQ50X9580) | C9: NOBLEX | D9: 207239 | E9: 1036193 | F9: 20.000039 | G9: 828954 | H9: Promo TV mundial | I9: 0.05 | J9: 0.15 | K9: Sin Int | L9: 12 | M9: 12 cuotas | N9: =+$G9/12 -> 69079.5 | O9: 0 | P9: 0 | Q9: =+N9 -> 69079.5 | R9: Sin Int | S9: 12 | T9: =+$G9/12 -> 69079.5 | U9: 9 | V9: =+G9/9 -> 92106 | X9: 0 | Y9: =+G9 -> 828954 | Z9: =+A9 -> 1002997 | AA9: 12 | AB9: 12 | AC9: Promo electro cuota sin interes Bancarias (todo en PAYWAY Si es cabal cód 12) | AD9: 46170 | AE9: 46203 | AF9: 0 | AG9: 12Sin IntBancarias+12Sin IntNaranja+9Tuya
A10: 1003056 | B10: Smart TV 50" UHD 4K Titan OS - AOC (50U7345/77I) | C10: AOC | D10: 167160 | E10: 835800 | F10: 20 | G10: 668640 | H10: Promo TV mundial | I10: 0.05 | J10: 0.15 | K10: Sin Int | L10: 12 | M10: 12 cuotas | N10: =+$G10/12 -> 55720 | O10: 0 | P10: 0 | Q10: =+N10 -> 55720 | R10: Sin Int | S10: 12 | T10: =+$G10/12 -> 55720 | U10: 9 | V10: =+G10/9 -> 74293.333 | X10: 0 | Y10: =+G10 -> 668640 | Z10: =+A10 -> 1003056 | AA10: 12 | AB10: 12 | AC10: Promo electro cuota sin interes Bancarias (todo en PAYWAY Si es cabal cód 12) | AD10: 46170 | AE10: 46203 | AF10: 0 | AG10: 12Sin IntBancarias+12Sin IntNaranja+9Tuya
A11: 1000847 | B11: Smart TV 55" UHD 4K Borderless Titan OS - PHILIPS (55PUD7309/77) | C11: PHILIPS | D11: 213169 | E11: 1065844 | F11: 20.000019 | G11: 852675 | H11: Promo TV mundial | I11: 0.05 | J11: 0.15 | K11: Sin Int | L11: 12 | M11: 12 cuotas | N11: =+$G11/12 -> 71056.25 | O11: 0 | P11: 0 | Q11: =+N11 -> 71056.25 | R11: Sin Int | S11: 12 | T11: =+$G11/12 -> 71056.25 | U11: 9 | V11: =+G11/9 -> 94741.667 | X11: 0 | Y11: =+G11 -> 852675 | Z11: =+A11 -> 1000847 | AA11: 12 | AB11: 12 | AC11: Promo electro cuota sin interes Bancarias (todo en PAYWAY Si es cabal cód 12) | AD11: 46170 | AE11: 46203 | AF11: 0 | AG11: 12Sin IntBancarias+12Sin IntNaranja+9Tuya
A12: 1002569 | B12: Smart TV 55" UHD 4K Google TV - TCL (55V6C) | C12: TCL | D12: 208588.16 | E12: 1042939.2 | F12: 20.000031 | G12: 834351 | H12: Promo TV mundial | I12: 0.05 | J12: 0.15 | K12: Sin Int | L12: 12 | M12: 12 cuotas | N12: =+$G12/12 -> 69529.25 | O12: 0 | P12: 0 | Q12: =+N12 -> 69529.25 | R12: Sin Int | S12: 12 | T12: =+$G12/12 -> 69529.25 | U12: 9 | V12: =+G12/9 -> 92705.667 | X12: 0 | Y12: =+G12 -> 834351 | Z12: =+A12 -> 1002569 | AA12: 12 | AB12: 12 | AC12: Promo electro cuota sin interes Bancarias (todo en PAYWAY Si es cabal cód 12) | AD12: 46170 | AE12: 46203 | AF12: 0 | AG12: 12Sin IntBancarias+12Sin IntNaranja+9Tuya
A13: 1002563 | B13: Smart TV 60" UHD 4K Google TV - BGH (PNE040306) | C13: BGH | D13: 242780 | E13: 1213900 | F13: 20 | G13: 971120 | H13: Promo TV mundial | I13: 0.05 | J13: 0.15 | K13: Sin Int | L13: 12 | M13: 12 cuotas | N13: =+$G13/12 -> 80926.667 | O13: 0 | P13: 0 | Q13: =+N13 -> 80926.667 | R13: Sin Int | S13: 12 | T13: =+$G13/12 -> 80926.667 | U13: 9 | V13: =+G13/9 -> 107902.22 | X13: 0 | Y13: =+G13 -> 971120 | Z13: =+A13 -> 1002563 | AA13: 12 | AB13: 12 | AC13: Promo electro cuota sin interes Bancarias (todo en PAYWAY Si es cabal cód 12) | AD13: 46170 | AE13: 46203 | AF13: 0 | AG13: 12Sin IntBancarias+12Sin IntNaranja+9Tuya
... A19: 1001272 | B19: Vitroconvector Electrico 1500W con Turbo Forzador Pie Pared - CRIVEL (GPH-15 T) | C19: CRIVEL | D19: 41901.11 | E19: 209505.11 | F19: 20.000042 | G19: 167604 | H19: Promo TV mundial | I19: 0.05 | J19: 0.15 | K19: Sin Int | L19: 12 | M19: 12 cuotas | N19: =+$G19/12 -> 13967 | O19: 0 | P19: 0 | Q19: =+N19 -> 13967 | R19: Sin Int | S19: 12 | T19: =+$G19/12 -> 13967 | U19: 9 | V19: =+G19/9 -> 18622.667 | X19: 0 | Y19: =+G19 -> 167604 | Z19: =+A19 -> 1001272 | AA19: 12 | AB19: 12 | AC19: Promo electro cuota sin interes Bancarias (todo en PAYWAY Si es cabal cód 12) | AD19: 46170 | AE19: 46203 | AF19: 0 | AG19: 12Sin IntBancarias+12Sin IntNaranja+9Tuya
A20: 1002394 | B20: Balanza de Cocina LCD Digital hasta 3kg Tactil Apagado Automatico - PHILCO (BC24B1PP) | C20: PHILCO | D20: $ 4.342,04 | E20: 25541.4 | F20: 0.17 | G20: 21199.36 | H20: Promo Apertura | I20: 0.05 | J20: 0.15 | K20: Sin Int | L20: 12 | M20: 12 cuotas | N20: =+$G20/12 -> 1766.6133 | O20: 0 | P20: 0 | Q20: =+N20 -> 1766.6133 | R20: Sin Int | S20: 12 | T20: =+$G20/12 -> 1766.6133 | U20: 9 | V20: =+G20/9 -> 2355.4844 | X20: 0 | Y20: =+G20 -> 21199.36 | Z20: =+A20 -> 1002394 | AA20: 12 | AB20: 12 | AC20: Promo electro cuota sin interes Bancarias (todo en PAYWAY Si es cabal cód 12) | AD20: 46175 | AE20: 46196 | AF20: 0 | AG20: 12Sin IntBancarias+12Sin IntNaranja+9Tuya
A21: 1002588 | B21: Cargador de Pared Gan Mega 30W Blanco - FOXBOX (7993) | C21: FOXBOX | D21: $ 7.385,23 | E21: 43442.54 | F21: 0.17 | G21: 36057.31 | H21: Promo Apertura | I21: 0.05 | J21: 0.15 | K21: Sin Int | L21: 12 | M21: 12 cuotas | N21: =+$G21/12 -> 3004.7758 | O21: 0 | P21: 0 | Q21: =+N21 -> 3004.7758 | R21: Sin Int | S21: 12 | T21: =+$G21/12 -> 3004.7758 | U21: 9 | V21: =+G21/9 -> 4006.3678 | X21: 0 | Y21: =+G21 -> 36057.31 | Z21: =+A21 -> 1002588 | AA21: 12 | AB21: 12 | AC21: Promo electro cuota sin interes Bancarias (todo en PAYWAY Si es cabal cód 12) | AD21: 46175 | AE21: 46196 | AF21: 0 | AG21: 12Sin IntBancarias+12Sin IntNaranja+9Tuya
A22: 90470 | B22: Cocina 51cm Blanca Candor S2 Gas Licuado - ESCORIAL (01.01-00070) | C22: ESCORIAL | D22: $ 78.930,45 | E22: 464296.77 | F22: 0.17 | G22: 385366.32 | H22: Promo Apertura | I22: 0.05 | J22: 0.15 | K22: Sin Int | L22: 12 | M22: 12 cuotas | N22: =+$G22/12 -> 32113.86 | O22: 0 | P22: 0 | Q22: =+N22 -> 32113.86 | R22: Sin Int | S22: 12 | T22: =+$G22/12 -> 32113.86 | U22: 9 | V22: =+G22/9 -> 42818.48 | X22: 0 | Y22: =+G22 -> 385366.32 | Z22: =+A22 -> 90470 | AA22: 12 | AB22: 12 | AC22: Promo electro cuota sin interes Bancarias (todo en PAYWAY Si es cabal cód 12) | AD22: 46175 | AE22: 46196 | AF22: 0 | AG22: 12Sin IntBancarias+12Sin IntNaranja+9Tuya
A23: 999680 | B23: Cocina 56cm Acero Inoxidable Classic - ESCORIAL (MASTER INOX CLASSIC) | C23: ESCORIAL | D23: $ 112.452,36 | E23: 661484.49 | F23: 0.17 | G23: 549032.12 | H23: Promo Apertura | I23: 0.05 | J23: 0.15 | K23: Sin Int | L23: 12 | M23: 12 cuotas | N23: =+$G23/12 -> 45752.677 | O23: 0 | P23: 0 | Q23: =+N23 -> 45752.677 | R23: Sin Int | S23: 12 | T23: =+$G23/12 -> 45752.677 | U23: 9 | V23: =+G23/9 -> 61003.569 | X23: 0 | Y23: =+G23 -> 549032.12 | Z23: =+A23 -> 999680 | AA23: 12 | AB23: 12 | AC23: Promo electro cuota sin interes Bancarias (todo en PAYWAY Si es cabal cód 12) | AD23: 46175 | AE23: 46196 | AF23: 0 | AG23: 12Sin IntBancarias+12Sin IntNaranja+9Tuya
A24: 82918 | B24: Cocina 56cm Blanca Enlozada Durpox Multigas - FLORENCIA (FLOR 5516F) | C24: FLORENCIA | D24: $ 98.317,84 | E24: 578340.25 | F24: 0.17 | G24: 480022.41 | H24: Promo Apertura | I24: 0.05 | J24: 0.15 | K24: Sin Int | L24: 12 | M24: 12 cuotas | N24: =+$G24/12 -> 40001.868 | O24: 0 | P24: 0 | Q24: =+N24 -> 40001.868 | R24: Sin Int | S24: 12 | T24: =+$G24/12 -> 40001.868 | U24: 9 | V24: =+G24/9 -> 53335.823 | X24: 0 | Y24: =+G24 -> 480022.41 | Z24: =+A24 -> 82918 | AA24: 12 | AB24: 12 | AC24: Promo electro cuota sin interes Bancarias (todo en PAYWAY Si es cabal cód 12) | AD24: 46175 | AE24: 46196 | AF24: 0 | AG24: 12Sin IntBancarias+12Sin IntNaranja+9Tuya
A25: 998097 | B25: Lavarropas Automatico C/Superior 6,5kg 800rpm Blanco EEA+ Concept - DREAN (Neo Fuzzy 6.8 Blanco) | C25: DREAN | D25: $ 132.297,37 | E25: 778219.81 | F25: 0.17 | G25: 645922.44 | H25: Promo Apertura | I25: 0.05 | J25: 0.15 | K25: Sin Int | L25: 12 | M25: 12 cuotas | N25: =+$G25/12 -> 53826.87 | O25: 0 | P25: 0 | Q25: =+N25 -> 53826.87 | R25: Sin Int | S25: 12 | T25: =+$G25/12 -> 53826.87 | U25: 9 | V25: =+G25/9 -> 71769.16 | X25: 0 | Y25: =+G25 -> 645922.44 | Z25: =+A25 -> 998097 | AA25: 12 | AB25: 12 | AC25: Promo electro cuota sin interes Bancarias (todo en PAYWAY Si es cabal cód 12) | AD25: 46175 | AE25: 46196 | AF25: 0 | AG25: 12Sin IntBancarias+12Sin IntNaranja+9Tuya
A26: 89807 | B26: Lavarropas Semiautomatico 7kg Blanco/Azul 7 Programas de Lavado - COLUMBIA (LSC 7000) | C26: COLUMBIA | D26: $ 43.564,77 | E26: 256263.38 | F26: 0.17 | G26: 212698.61 | H26: Promo Apertura | I26: 0.05 | J26: 0.15 | K26: Sin Int | L26: 12 | M26: 12 cuotas | N26: =+$G26/12 -> 17724.884 | O26: 0 | P26: 0 | Q26: =+N26 -> 17724.884 | R26: Sin Int | S26: 12 | T26: =+$G26/12 -> 17724.884 | U26: 9 | V26: =+G26/9 -> 23633.179 | X26: 0 | Y26: =+G26 -> 212698.61 | Z26: =+A26 -> 89807 | AA26: 12 | AB26: 12 | AC26: Promo electro cuota sin interes Bancarias (todo en PAYWAY Si es cabal cód 12) | AD26: 46175 | AE26: 46196 | AF26: 0 | AG26: 12Sin IntBancarias+12Sin IntNaranja+9Tuya
A27: 996526 | B27: Licuadora de Vaso 1.5Lts 500W Blanca 2 Velocidades + Pulsador - ATMA (LI8445AP) | C27: ATMA | D27: $ 15.849,01 | E27: 93229.46 | F27: 0.17 | G27: 77380.45 | H27: Promo Apertura | I27: 0.05 | J27: 0.15 | K27: Sin Int | L27: 12 | M27: 12 cuotas | N27: =+$G27/12 -> 6448.3708 | O27: 0 | P27: 0 | Q27: =+N27 -> 6448.3708 | R27: Sin Int | S27: 12 | T27: =+$G27/12 -> 6448.3708 | U27: 9 | V27: =+G27/9 -> 8597.8278 | X27: 0 | Y27: =+G27 -> 77380.45 | Z27: =+A27 -> 996526 | AA27: 12 | AB27: 12 | AC27: Promo electro cuota sin interes Bancarias (todo en PAYWAY Si es cabal cód 12) | AD27: 46175 | AE27: 46196 | AF27: 0 | AG27: 12Sin IntBancarias+12Sin IntNaranja+9Tuya
A28: 997700 | B28: Secarropas Centrifugo 6,5Kg 2800rpm Blanco/Azul - CODINI (AD65) | C28: CODINI | D28: $ 50.102,55 | E28: 294720.87 | F28: 0.17 | G28: 244618.32 | H28: Promo Apertura | I28: 0.05 | J28: 0.15 | K28: Sin Int | L28: 12 | M28: 12 cuotas | N28: =+$G28/12 -> 20384.86 | O28: 0 | P28: 0 | Q28: =+N28 -> 20384.86 | R28: Sin Int | S28: 12 | T28: =+$G28/12 -> 20384.86 | U28: 9 | V28: =+G28/9 -> 27179.813 | X28: 0 | Y28: =+G28 -> 244618.32 | Z28: =+A28 -> 997700 | AA28: 12 | AB28: 12 | AC28: Promo electro cuota sin interes Bancarias (todo en PAYWAY Si es cabal cód 12) | AD28: 46175 | AE28: 46196 | AF28: 0 | AG28: 12Sin IntBancarias+12Sin IntNaranja+9Tuya
A29: 97530 | B29: Tablet 3GB Ram 32GB Rom 8.7" Galaxy Tab A7 Lite Silver - SAMSUNG (SM-T220NZSDARO) | C29: SAMSUNG | D29: $ 83.811,64 | E29: 493009.63 | F29: 0.17 | G29: 409197.99 | H29: Promo Apertura | I29: 0.05 | J29: 0.15 | K29: Sin Int | L29: 12 | M29: 12 cuotas | N29: =+$G29/12 -> 34099.832 | O29: 0 | P29: 0 | Q29: =+N29 -> 34099.832 | R29: Sin Int | S29: 12 | T29: =+$G29/12 -> 34099.832 | U29: 9 | V29: =+G29/9 -> 45466.443 | X29: 0 | Y29: =+G29 -> 409197.99 | Z29: =+A29 -> 97530 | AA29: 12 | AB29: 12 | AC29: Promo electro cuota sin interes Bancarias (todo en PAYWAY Si es cabal cód 12) | AD29: 46175 | AE29: 46196 | AF29: 0 | AG29: 12Sin IntBancarias+12Sin IntNaranja+9Tuya
A30: 999516 | B30: Celular Galaxy A06 4GB Ram 64GB Rom Green - SAMSUNG (SM-A065MLGAARO) | C30: SAMSUNG | D30: CELULARES | E30: 383169 | F30: 24.48% - $ 93800 | G30: 289369 | H30: Dia del Padre | I30: 0.05 | J30: 0.08 | K30: Sin Int | L30: 6 | M30: 6 cuotas | N30: 48228.2 | O30: 0 | P30: 0 | Q30: 289369 | R30: Sin Int | S30: 6 | T30: 48228.167 | U30: 3 | V30: 96456.333 | X30: 0 | Y30: 289369 | Z30: 999516 | AA30: 6 | AB30: 6 | AC30: Promo electro cuota sin interes Bancarias (todo en PAYWAY Si es cabal cód 16) | AD30: 46186 | AE30: 46570 | AF30: 35 | AG30: 6Sin IntBancarias+6Sin IntNaranja+3Tuya
A31: 1000766 | B31: Celular Moto G15 4GB Ram 128GB Rom Verde - MOTOROLA (PB6D0034AR) | C31: MOTOROLA | D31: CELULARES | E31: 396449 | F31: 24.492% - $ 97100 | G31: 299349 | H31: Dia del Padre | I31: 0.05 | J31: 0.08 | K31: Sin Int | L31: 6 | M31: 6 cuotas | N31: 49891.5 | O31: 0 | P31: 0 | Q31: 299349 | R31: Sin Int | S31: 6 | T31: 49891.5 | U31: 3 | V31: 99783 | X31: 0 | Y31: 299349 | Z31: 1000766 | AA31: 6 | AB31: 6 | AC31: Promo electro cuota sin interes Bancarias (todo en PAYWAY Si es cabal cód 16) | AD31: 46186 | AE31: 46570 | AF31: 12 | AG31: 6Sin IntBancarias+6Sin IntNaranja+3Tuya
A32: 1000853 | B32: Celular Redmi 14C Midnight Black 4GB Ram 256GB Rom | C32: XIAOMI | D32: ELECTRODOMESTICOS | E32: 495749 | F32: 24.488% - $ 121400 | G32: 374349 | H32: Dia del Padre | I32: 0.05 | J32: 0.08 | K32: Sin Int | L32: 6 | M32: 6 cuotas | N32: 62391.5 | O32: 0 | P32: 0 | Q32: 374349 | R32: Sin Int | S32: 6 | T32: 62391.5 | U32: 3 | V32: 124783 | X32: 0 | Y32: 374349 | Z32: 1000853 | AA32: 6 | AB32: 6 | AC32: Promo electro cuota sin interes Bancarias (todo en PAYWAY Si es cabal cód 16) | AD32: 46186 | AE32: 46570 | AF32: 12 | AG32: 6Sin IntBancarias+6Sin IntNaranja+3Tuya
A33: 1002556 | B33: Celular Moto G15 SE 4GB Ram 256GB Rom Verde - MOTOROLA (PB6D0088AR) | C33: MOTOROLA | D33: CELULARES | E33: 462439 | F33: 24.479% - $ 113200 | G33: 349239 | H33: Dia del Padre | I33: 0.05 | J33: 0.08 | K33: Sin Int | L33: 6 | M33: 6 cuotas | N33: 58206.5 | O33: 0 | P33: 0 | Q33: 349239 | R33: Sin Int | S33: 6 | T33: 58206.5 | U33: 3 | V33: 116413 | X33: 0 | Y33: 349239 | Z33: 1002556 | AA33: 6 | AB33: 6 | AC33: Promo electro cuota sin interes Bancarias (todo en PAYWAY Si es cabal cód 16) | AD33: 46186 | AE33: 46570 | AF33: 11 | AG33: 6Sin IntBancarias+6Sin IntNaranja+3Tuya
A34: 1002968 | B34: Celular Redmi Note 14 Pro 8GB Ram 256GB Rom Aurora Purple - XIAOMI (MZB0KBZAR) | C34: XIAOMI | D34: CELULARES | E34: 991499 | F34: 24.488% - $ 242800 | G34: 748699 | H34: Dia del Padre | I34: 0.05 | J34: 0.08 | K34: Sin Int | L34: 6 | M34: 6 cuotas | N34: 124783.2 | O34: 0 | P34: 0 | Q34: 748699 | R34: Sin Int | S34: 6 | T34: 124783.17 | U34: 3 | V34: 249566.33 | X34: 0 | Y34: 748699 | Z34: 1002968 | AA34: 6 | AB34: 6 | AC34: Promo electro cuota sin interes Bancarias (todo en PAYWAY Si es cabal cód 16) | AD34: 46186 | AE34: 46570 | AF34: 12 | AG34: 6Sin IntBancarias+6Sin IntNaranja+3Tuya
A35: 1003291 | B35: Celular Moto G56 5G 8GB Ram 256GB Rom Gray Mist - MOTOROLA (PB800002AR) | C35: MOTOROLA | D35: CELULARES | E35: 792789 | F35: 24.483% - $ 194100 | G35: 598689 | H35: Dia del Padre | I35: 0.05 | J35: 0.08 | K35: Sin Int | L35: 6 | M35: 6 cuotas | N35: 99781.5 | O35: 0 | P35: 0 | Q35: 598689 | R35: Sin Int | S35: 6 | T35: 99781.5 | U35: 3 | V35: 199563 | X35: 0 | Y35: 598689 | Z35: 1003291 | AA35: 6 | AB35: 6 | AC35: Promo electro cuota sin interes Bancarias (todo en PAYWAY Si es cabal cód 16) | AD35: 46186 | AE35: 46570 | AF35: 18 | AG35: 6Sin IntBancarias+6Sin IntNaranja+3Tuya
A36: 94651 | B36: Motosierra Naftera 2T 52cc 2.5Hp Esp - GARDEN PLUS (PROM-52GC) | C36: GARDEN PLUS | D36: TALLER | E36: 142649 | F36: 23.484% - $ 33500 | G36: 109149 | H36: Dia del Padre | I36: 0.05 | J36: 0.08 | K36: Sin Int | L36: 6 | M36: 6 cuotas | N36: 18191.5 | O36: 0 | P36: 0 | Q36: 109149 | R36: Sin Int | S36: 6 | T36: 18191.5 | U36: 3 | V36: 36383 | X36: 0 | Y36: 109149 | Z36: 94651 | AA36: 6 | AB36: 6 | AC36: Promo electro cuota sin interes Bancarias (todo en PAYWAY Si es cabal cód 16) | AD36: 46186 | AE36: 46570 | AF36: 30 | AG36: 6Sin IntBancarias+6Sin IntNaranja+3Tuya
A37: 95162 | B37: Hidrolavadora 1200W 70Bar | C37: LUSQTOFF | D37: ELECTRODOMESTICOS | E37: 156469 | F37: 23.519% - $ 36800 | G37: 119669 | H37: Dia del Padre | I37: 0.05 | J37: 0.08 | K37: Sin Int | L37: 6 | M37: 6 cuotas | N37: 19944.8 | O37: 0 | P37: 0 | Q37: 119669 | R37: Sin Int | S37: 6 | T37: 19944.833 | U37: 3 | V37: 39889.667 | X37: 0 | Y37: 119669 | Z37: 95162 | AA37: 6 | AB37: 6 | AC37: Promo electro cuota sin interes Bancarias (todo en PAYWAY Si es cabal cód 16) | AD37: 46186 | AE37: 46570 | AF37: 30 | AG37: 6Sin IntBancarias+6Sin IntNaranja+3Tuya
A38: 95165 | B38: Lijadora Orbital 260W 220V-50hz - LUSQTOFF (LOL260-8) | C38: LUSQTOFF | D38: TALLER | E38: 97019 | F38: 16.698% - $ 16200 | G38: 80819 | H38: Dia del Padre | I38: 0.05 | J38: 0.15 | K38: Sin Int | L38: 12 | M38: 12 cuotas | N38: 6734.9 | O38: 0 | P38: 0 | Q38: 80819 | R38: Sin Int | S38: 12 | T38: 6734.9167 | U38: 6 | V38: 13469.833 | X38: 0 | Y38: 80819 | Z38: 95165 | AA38: 12 | AB38: 12 | AC38: Promo electro cuota sin interes Bancarias (todo en PAYWAY) | AD38: 46186 | AE38: 46570 | AF38: 16 | AG38: 12Sin IntBancarias+12Sin IntNaranja+6Tuya
A39: 95168 | B39: Mini Torno 150W 220V-50hz con Accesorios - LUSQTOFF (MTL150-9) | C39: LUSQTOFF | D39: TALLER | E39: 122299 | F39: 23.467% - $ 28700 | G39: 93599 | H39: Dia del Padre | I39: 0.05 | J39: 0.08 | K39: Sin Int | L39: 6 | M39: 6 cuotas | N39: 15599.8 | O39: 0 | P39: 0 | Q39: 93599 | R39: Sin Int | S39: 6 | T39: 15599.833 | U39: 3 | V39: 31199.667 | X39: 0 | Y39: 93599 | Z39: 95168 | AA39: 6 | AB39: 6 | AC39: Promo electro cuota sin interes Bancarias (todo en PAYWAY Si es cabal cód 16) | AD39: 46186 | AE39: 46570 | AF39: 14 | AG39: 6Sin IntBancarias+6Sin IntNaranja+3Tuya
A40: 95171 | B40: Kit Herramientas 108 Piezas Caja Plastica - LUSQTOFF (SET108LQ) | C40: LUSQTOFF | D40: TALLER | E40: 129359 | F40: 16.698% - $ 21600 | G40: 107759 | H40: Dia del Padre | I40: 0.05 | J40: 0.15 | K40: Sin Int | L40: 12 | M40: 12 cuotas | N40: 8979.9 | O40: 0 | P40: 0 | Q40: 107759 | R40: Sin Int | S40: 12 | T40: 8979.9167 | U40: 6 | V40: 17959.833 | X40: 0 | Y40: 107759 | Z40: 95171 | AA40: 12 | AB40: 12 | AC40: Promo electro cuota sin interes Bancarias (todo en PAYWAY) | AD40: 46186 | AE40: 46570 | AF40: 12 | AG40: 12Sin IntBancarias+12Sin IntNaranja+6Tuya
A41: 96063 | B41: Taladro a Bateria con Percutor 18V 1.5A - LUSQTOFF (ATL18-8B) | C41: LUSQTOFF | D41: TALLER | E41: 153629 | F41: 23.498% - $ 36100 | G41: 117529 | H41: Dia del Padre | I41: 0.05 | J41: 0.08 | K41: Sin Int | L41: 6 | M41: 6 cuotas | N41: 19588.2 | O41: 0 | P41: 0 | Q41: 117529 | R41: Sin Int | S41: 6 | T41: 19588.167 | U41: 3 | V41: 39176.333 | X41: 0 | Y41: 117529 | Z41: 96063 | AA41: 6 | AB41: 6 | AC41: Promo electro cuota sin interes Bancarias (todo en PAYWAY Si es cabal cód 16) | AD41: 46186 | AE41: 46570 | AF41: 14 | AG41: 6Sin IntBancarias+6Sin IntNaranja+3Tuya
... A49: 1000607 | B49: Soldadora Inverter 220V 50Hz 120A con Escuadras - LUSQTOFF (MEGAIRON140) | C49: LUSQTOFF | D49: TALLER | E49: 293269 | F49: 23.494% - $ 68900 | G49: 224369 | H49: Dia del Padre | I49: 0.05 | J49: 0.08 | K49: Sin Int | L49: 6 | M49: 6 cuotas | N49: 37394.8 | O49: 0 | P49: 0 | Q49: 224369 | R49: Sin Int | S49: 6 | T49: 37394.833 | U49: 3 | V49: 74789.667 | X49: 0 | Y49: 224369 | Z49: 1000607 | AA49: 6 | AB49: 6 | AC49: Promo electro cuota sin interes Bancarias (todo en PAYWAY Si es cabal cód 16) | AD49: 46186 | AE49: 46570 | AF49: 11 | AG49: 6Sin IntBancarias+6Sin IntNaranja+3Tuya
A50: 1001086 | B50: Amoladora Angular 850W 11000rpm 125mm 220V50Hz - LUSQTOFF (AML850-9) | C50: LUSQTOFF | D50: TALLER | E50: 104299 | F50: 18.121% - $ 18900 | G50: 85399 | H50: Dia del Padre | I50: 0.05 | J50: 0.1 | K50: Sin Int | L50: 9 | M50: 9 cuotas | N50: 9488.8 | O50: 0 | P50: 0 | Q50: 85399 | R50: Sin Int | S50: 9 | T50: 9488.7778 | U50: 5 | V50: 17079.8 | X50: 0 | Y50: 85399 | Z50: 1001086 | AA50: #N/A | AB50: #N/A | AC50: #N/A | AD50: 46186 | AE50: 46570 | AF50: 64 | AG50: 9Sin IntBancarias+9Sin IntNaranja+5Tuya
A51: 1001087 | B51: Taladro Atornillador Inalambrico 12v Caja con Accesorios - LUSQTOFF (TAL12-8A) | C51: LUSQTOFF | D51: TALLER | E51: 152899 | F51: 23.48% - $ 35900 | G51: 116999 | H51: Dia del Padre | I51: 0.05 | J51: 0.08 | K51: Sin Int | L51: 6 | M51: 6 cuotas | N51: 19499.8 | O51: 0 | P51: 0 | Q51: 116999 | R51: Sin Int | S51: 6 | T51: 19499.833 | U51: 3 | V51: 38999.667 | X51: 0 | Y51: 116999 | Z51: 1001087 | AA51: 6 | AB51: 6 | AC51: Promo electro cuota sin interes Bancarias (todo en PAYWAY Si es cabal cód 16) | AD51: 46186 | AE51: 46570 | AF51: 16 | AG51: 6Sin IntBancarias+6Sin IntNaranja+3Tuya
A52: 1003220 | B52: Hidrolavadora 1400W 1100Bar 340Lts/Hora - ULTRACOMB (HDL400) | C52: ULTRACOMB | D52: TALLER | E52: 164979 | F52: 23.518% - $ 38800 | G52: 126179 | H52: Dia del Padre | I52: 0.05 | J52: 0.08 | K52: Sin Int | L52: 6 | M52: 6 cuotas | N52: 21029.8 | O52: 0 | P52: 0 | Q52: 126179 | R52: Sin Int | S52: 6 | T52: 21029.833 | U52: 3 | V52: 42059.667 | X52: 0 | Y52: 126179 | Z52: 1003220 | AA52: 6 | AB52: 6 | AC52: Promo electro cuota sin interes Bancarias (todo en PAYWAY Si es cabal cód 16) | AD52: 46186 | AE52: 46570 | AF52: 16 | AG52: 6Sin IntBancarias+6Sin IntNaranja+3Tuya

Sheet Hoja2

Sheet Asesora Politicas
F1: =+_xlfn.XLOOKUP('Asesora Politicas'!C4, Productos!A:A, Productos!AE:AE, "VER", 0, -1) -> 46570 | G1: 0.05 | L1: public:
F2: Bienvenido/a soy Fina tu asesora de Políticas Financieras en revista | L2: =+_xlfn.XLOOKUP(C4, Productos!A:A, Productos!K:K, "Articulo no encontrado", 0, -1) -> Sin Int
D3: Con Garantía Extendida: | G3: Cliente Externo | H3: Afiliados | L3: finan:
C4: 1000124 | E4: Desc: | F4: =+_xlfn.XLOOKUP(C4, Productos!A:A, Productos!B:B) -> Taladro Atornillador 300W - LUSQTOFF (TAL300-8) | G4: =SUMIFS(Productos!G:G, Productos!A:A, $C$4, Productos!AD:AD, "<" & TODAY()+1, Productos!AE:AE, ">" & TODAY()-1) -> 67349 | H4: =+IF(IFERROR(SEARCH("Proveed", F8, 1), 0)=0, IF(_xlfn.XLOOKUP($C$4, Productos!A:A, Productos!I:I, 0, 0, -1)=0, "Sin descuentos Afiliado", _xlfn.XLOOKUP($C$4, Productos!A:A, Productos!G:G, 0, 0, -1)*(1-_xlfn.XLOOKUP($C$4, Productos!A:A, Productos!I:I, 0, 0, -1))), "Puede llevar más tiempo más beneficio") -> 63981.55 | L4: =+_xlfn.XLOOKUP(C4, Productos!A:A, Productos!L:L, 0, 0, -1) -> 12
C5: =CONCATENATE("Ubicación Hoja Producto, Celda A", MATCH(C4,Productos!A:A,0)) -> Ubicación Hoja Producto, Celda A44
F7: Tipo de Oferta | G7: cuotas hasta
E8: Publicado en | F8: =+IF(TODAY()<(F1+1), IF(L2="", "Ingrese Cod Articulo como número", IF(L2="No se encuentra el articulo", "No se encuentra el articulo revisar Código", IF(L2="Sin Int", "Cuotas Sin Interes hasta", IF(L2="Peque", "Cuotas en Peque Tasas Hasta:", IF(IFERROR(SEARCH("Prove", L2,1), 0)>0, "Oferta Convenio con Proveedor", "Oferta de Contado -No tiene cuot sin int-"))))), "Estas Ofertas ya no están en Vigencia") -> Cuotas Sin Interes hasta | G8: =+SUMIFS(Productos!L:L, Productos!A:A, $C$4, Productos!AD:AD, "<" & TODAY()+1, Productos!AE:AE, ">" & TODAY()-1) -> 12
F9: =IF(F1<TODAY(), "YA no está en vigencia", IF(_xlfn.XLOOKUP(C4, Productos!A:A, Productos!AD:AD, "No encontramos el BC buscado", 0, -1)>TODAY()+1, "Todavia no está en Vigencia", CONCATENATE("Vigente hasta: ", TEXT(F1, "dd mmm"), " Segmento: ", _xlfn.XLOOKUP(C4, Productos!A:A, Productos!H:H, 0, 0, -1)))) -> Vigente hasta: 02 jul Segmento: Dia del Padre
E11: Según la | F11: =IF(F8="Estas Ofertas ya no están en Vigencia", "_", +IF(F8= "Ingrese Cod Articulo como número", "Ingrese Cod Articulo como número", IF(F8="Oferta de Contado -No tiene cuot sin int-", "NO tiene desc por pago contado", IF(G8<3, "NO tiene desc por pago contado", "Tiene Descuento por Pago Contado")))) -> Tiene Descuento por Pago Contado | G11: =AVERAGEIFS(Productos!J:J, Productos!A:A, $C$4, Productos!AD:AD, "<" & TODAY()+1, Productos!AE:AE, ">" & TODAY()-1) -> 0.15 | H11: =_xlfn.XLOOKUP(C4, Productos!A:A, Productos!G:G, 0, 0,-1)*(1-G11) -> 57246.65 | I11: =IF(IFERROR(SEARCH("Oferta de cont",F8,1),0)>0, _xlfn.CONCAT("Oferta contado, cargar descuento",_xlfn.XLOOKUP(C4,Productos!A:A,Productos!F:F,"",0,-1),"Ahorro manual"), IF(G11>0, _xlfn.CONCAT("Afiliados contado ",ROUND(IFERROR(H4*(1-G11), ""), 1)), "")) -> Afiliados contado 54384.3 | J11: =+IF(IFERROR(SEARCH("Mundial Clubes", F9, 1), 0)=0, "", CONCATENATE("Contado Afiliado ", TEXT(H11*0.95, "$#,##0.00")))
E12: política: | F12: =IF(F8="Estas Ofertas ya no están en Vigencia", "_", IF(IFERROR(SEARCH("Peque", F8, 1), FALSE()), CONCATENATE("Peque Tasa tiene hasta ", G8, " cuotas"), IF(IFERROR(SEARCH("Oferta de Contado", F8, 1),FALSE()), "Este articulo NO tiene peque tasas", IF(G8>5, CONCATENATE("Peque Tasa tiene hasta ", IF(G8<11, 12, 18), " cuotas"), "Este articulo NO tiene Peque tasa")))) -> Peque Tasa tiene hasta 18 cuotas | G12: Valores Aproximados de Cuotas
F13: =IF(F8="Estas Ofertas ya no están en Vigencia","_",IF(IFERROR(SEARCH("Prove", L2,1), 0)>0, "_", IF(IFERROR(SEARCH("Oferta de cont", F8, 1), 0)>0,"No tiene cuotas sin interés", "Tarj Bersa/Sta Fe/Corrientes/Credicoop/Comafi /Formosa/Chaco, sin int "&_xlfn.XLOOKUP(CONCATENATE($L$2," ",$L$4),'convinaciones fina'!A:A,'convinaciones fina'!D:D,"REVISAR")))) -> Tarj Bersa/Sta Fe/Corrientes/Credicoop/Comafi /Formosa/Chaco, sin int hasta 12 cuotas | G13: =ROUND(IF(IFERROR(SEARCH("hasta 3", F13, 1), FALSE()), SUMIFS(Productos!G:G, Productos!A:A, $C$4, Productos!AD:AD, "<" & TODAY()+1, Productos!AE:AE, ">" & TODAY()-1)/3, IF(IFERROR(SEARCH("hasta 6", F13, 1), FALSE()), SUMIFS(Productos!G:G, Productos!A:A, $C$4, Productos!AD:AD, "<" & TODAY()+1, Productos!AE:AE, ">" & TODAY()-1)/6, IF(IFERROR(SEARCH("hasta 9", F13, 1), FALSE()), SUMIFS(Productos!G:G, Productos!A:A, $C$4, Productos!AD:AD, "<" & TODAY()+1, Productos!AE:AE, ">" & TODAY()-1)/9, IF(IFERROR(SEARCH("hasta 10", F13, 1), FALSE()), SUMIFS(Productos!G:G, Productos!A:A, $C$4, Productos!AD:AD, "<" & TODAY()+1, Productos!AE:AE, ">" & TODAY()-1)/10, IF(IFERROR(SEARCH("hasta 12", F13, 1), FALSE()), SUMIFS(Productos!G:G, Productos!A:A, $C$4, Productos!AD:AD, "<" & TODAY()+1, Productos!AE:AE, ">" & TODAY()-1)/12, IF(IFERROR(SEARCH("hasta 18", F13, 1), FALSE()), SUMIFS(Productos!G:G, Productos!A:A, $C$4, Productos!AD:AD, "<" & TODAY()+1, Productos!AE:AE, ">" & TODAY()-1)/18, IF(IFERROR(SEARCH("hasta 24", F13, 1), FALSE()), SUMIFS(Productos!G:G, Productos!A:A, $C$4, Productos!AD:AD, "<" & TODAY()+1, Productos!AE:AE, ">" & TODAY()-1)/24, IF(IFERROR(SEARCH("hasta 1 ", F13, 1), FALSE()), SUMIFS(Productos!G:G, Productos!A:A, $C$4, Productos!AD:AD, "<" & TODAY()+1, Productos!AE:AE, ">" & TODAY()-1),0)))))))), 2) -> 5612.42 | H13: =+IF(G13>1, ROUNDUP(G13*0.95,1), "") -> 5331.8
F14: =IF(F8="Estas Ofertas ya no están en Vigencia","_",IF(IFERROR(SEARCH("Prove", L2,1), 0)>0, "Política comercial vigente", IF(IFERROR(SEARCH("Oferta de cont", F8, 1), 0)>0,"No tiene cuotas sin interés","Bcos Macro, Nación, Gal, BBVA, sin int "&_xlfn.XLOOKUP(CONCATENATE(_xlfn.XLOOKUP(C4, Productos!A:A, Productos!R:R, 0, 0, -1)," ",_xlfn.XLOOKUP(C4, Productos!A:A, Productos!S:S, 0, 0, -1)),'convinaciones fina'!B:B,'convinaciones fina'!K:K,"REVISAR")))) -> Bcos Macro, Nación, Gal, BBVA, sin int hasta 6 cuotas | H14: =+IF(G14>1, ROUNDUP(G14*0.95,1), "")
F15: =IF(F8="Estas Ofertas ya no están en Vigencia","_",IF(IFERROR(SEARCH("Prove", L2,1), 0)>0, "_", IF(IFERROR(SEARCH("Oferta de cont", F8, 1), 0)>0,"No tiene cuotas sin interés","NARANJA X, sin int "&_xlfn.XLOOKUP(CONCATENATE(_xlfn.XLOOKUP(C4, Productos!A:A, Productos!R:R, 0, 0, -1)," ",_xlfn.XLOOKUP(C4, Productos!A:A, Productos!S:S, 0, 0, -1)),'convinaciones fina'!B:B,'convinaciones fina'!E:E,"REVISAR")))) -> NARANJA X, sin int hasta 12 cuotas | G15: =ROUND(IF(IFERROR(SEARCH("hasta 3", F15, 1), FALSE()), SUMIFS(Productos!G:G, Productos!A:A, $C$4, Productos!AD:AD, "<" & TODAY()+1, Productos!AE:AE, ">" & TODAY()-1)/3, IF(IFERROR(SEARCH("hasta 6", F15, 1), FALSE()), SUMIFS(Productos!G:G, Productos!A:A, $C$4, Productos!AD:AD, "<" & TODAY()+1, Productos!AE:AE, ">" & TODAY()-1)/6, IF(IFERROR(SEARCH("hasta 9", F15, 1), FALSE()), SUMIFS(Productos!G:G, Productos!A:A, $C$4, Productos!AD:AD, "<" & TODAY()+1, Productos!AE:AE, ">" & TODAY()-1)/9, IF(IFERROR(SEARCH("hasta 10", F15, 1), FALSE()), SUMIFS(Productos!G:G, Productos!A:A, $C$4, Productos!AD:AD, "<" & TODAY()+1, Productos!AE:AE, ">" & TODAY()-1)/10, IF(IFERROR(SEARCH("hasta 12", F15, 1), FALSE()), SUMIFS(Productos!G:G, Productos!A:A, $C$4, Productos!AD:AD, "<" & TODAY()+1, Productos!AE:AE, ">" & TODAY()-1)/12, IF(IFERROR(SEARCH("hasta 18", F15, 1), FALSE()), SUMIFS(Productos!G:G, Productos!A:A, $C$4, Productos!AD:AD, "<" & TODAY()+1, Productos!AE:AE, ">" & TODAY()-1)/18, IF(IFERROR(SEARCH("hasta 24", F15, 1), FALSE()), SUMIFS(Productos!G:G, Productos!A:A, $C$4, Productos!AD:AD, "<" & TODAY()+1, Productos!AE:AE, ">" & TODAY()-1)/24, IF(IFERROR(SEARCH("hasta 1 ", F15, 1), FALSE()), SUMIFS(Productos!G:G, Productos!A:A, $C$4, Productos!AD:AD, "<" & TODAY()+1, Productos!AE:AE, ">" & TODAY()-1),0)))))))), 2) -> 5612.42 | H15: =+IF(G15>1, ROUNDUP(G15*0.95,1), "") -> 5331.8
F16: =IF(F8="Estas Ofertas ya no están en Vigencia","_",IF(IFERROR(SEARCH("Prove", L2,1), 0)>0, "_", IF(IFERROR(SEARCH("Oferta de cont", F8, 1), 0)>0,"No tiene cuotas sin interés","TUYA NBCH, "&CONCATENATE(_xlfn.XLOOKUP(C4, Productos!A:A, Productos!R:R, 0, 0, -1)," hasta ",_xlfn.XLOOKUP(C4, Productos!A:A, Productos!U:U, 0, 0, -1), " cuotas")))) -> TUYA NBCH, Sin Int hasta 6 cuotas | G16: =ROUND(IF(IFERROR(SEARCH("hasta 3", F16, 1), FALSE()), SUMIFS(Productos!G:G, Productos!A:A, $C$4, Productos!AD:AD, "<" & TODAY()+1, Productos!AE:AE, ">" & TODAY()-1)/3, IF(IFERROR(SEARCH("hasta 5", F16, 1), FALSE()), SUMIFS(Productos!G:G, Productos!A:A, $C$4, Productos!AD:AD, "<" & TODAY()+1, Productos!AE:AE, ">" & TODAY()-1)/5, IF(IFERROR(SEARCH("hasta 10", F16, 1), FALSE()), SUMIFS(Productos!G:G, Productos!A:A, $C$4, Productos!AD:AD, "<" & TODAY()+1, Productos!AE:AE, ">" & TODAY()-1)/10, IF(IFERROR(SEARCH("hasta 12", F16, 1), FALSE()), SUMIFS(Productos!G:G, Productos!A:A, $C$4, Productos!AD:AD, "<" & TODAY()+1, Productos!AE:AE, ">" & TODAY()-1)/12, IF(IFERROR(SEARCH("hasta 18", F16, 1), FALSE()), SUMIFS(Productos!G:G, Productos!A:A, $C$4, Productos!AD:AD, "<" & TODAY()+1, Productos!AE:AE, ">" & TODAY()-1)/18, IF(IFERROR(SEARCH("hasta 24", F16, 1), FALSE()), SUMIFS(Productos!G:G, Productos!A:A, $C$4, Productos!AD:AD, "<" & TODAY()+1, Productos!AE:AE, ">" & TODAY()-1)/24, IF(IFERROR(SEARCH("hasta 1 ", F16, 1), FALSE()), SUMIFS(Productos!G:G, Productos!A:A, $C$4, Productos!AD:AD, "<" & TODAY()+1, Productos!AE:AE, ">" & TODAY()-1),0))))))), 2) -> 0 | H16: =+IF(G16>1, ROUNDUP(G16*0.95,1), "")
F17: =IF(F8="Estas Ofertas ya no están en Vigencia","_",IF(IFERROR(SEARCH("Prove", L2,1), 0)>0, "Política comercial vigente", IF(IFERROR(SEARCH("Oferta de cont", F8, 1), 0)>0,"No tiene cuotas sin interés","Sidecreer, sin int "&_xlfn.XLOOKUP(CONCATENATE(_xlfn.XLOOKUP(C4, Productos!A:A, Productos!R:R, 0, 0, -1)," ",_xlfn.XLOOKUP(C4, Productos!A:A, Productos!S:S, 0, 0, -1)),'convinaciones fina'!B:B,'convinaciones fina'!G:G,"REVISAR")))) -> Sidecreer, sin int hasta 6 cuotas | G17: =ROUND(IF(IFERROR(SEARCH("hasta 3", F17, 1), FALSE()), SUMIFS(Productos!G:G, Productos!A:A, $C$4, Productos!AD:AD, "<" & TODAY()+1, Productos!AE:AE, ">" & TODAY()-1)/3, IF(IFERROR(SEARCH("hasta 6", F17, 1), FALSE()), SUMIFS(Productos!G:G, Productos!A:A, $C$4, Productos!AD:AD, "<" & TODAY()+1, Productos!AE:AE, ">" & TODAY()-1)/6, IF(IFERROR(SEARCH("hasta 10", F17, 1), FALSE()), SUMIFS(Productos!G:G, Productos!A:A, $C$4, Productos!AD:AD, "<" & TODAY()+1, Productos!AE:AE, ">" & TODAY()-1)/10, IF(IFERROR(SEARCH("hasta 12", F17, 1), FALSE()), SUMIFS(Productos!G:G, Productos!A:A, $C$4, Productos!AD:AD, "<" & TODAY()+1, Productos!AE:AE, ">" & TODAY()-1)/12, IF(IFERROR(SEARCH("hasta 18", F17, 1), FALSE()), SUMIFS(Productos!G:G, Productos!A:A, $C$4, Productos!AD:AD, "<" & TODAY()+1, Productos!AE:AE, ">" & TODAY()-1)/18, IF(IFERROR(SEARCH("hasta 24", F17, 1), FALSE()), SUMIFS(Productos!G:G, Productos!A:A, $C$4, Productos!AD:AD, "<" & TODAY()+1, Productos!AE:AE, ">" & TODAY()-1)/24, IF(IFERROR(SEARCH("hasta 1 ", F17, 1), FALSE()), SUMIFS(Productos!G:G, Productos!A:A, $C$4, Productos!AD:AD, "<" & TODAY()+1, Productos!AE:AE, ">" & TODAY()-1),0))))))), 2) -> 11224.83 | H17: =+IF(G17>1, ROUNDUP(G17*0.95,1), "") -> 10663.6
F18: =IF(F8="Estas Ofertas ya no están en Vigencia","_",IF(IFERROR(SEARCH("Prove", L2,1), 0)>0, "Política comercial vigente", IF(IFERROR(SEARCH("Oferta de cont", F8, 1), 0)>0,"No tiene cuotas sin interés","Consumax Sin Desc Afiliado, sin int "&_xlfn.XLOOKUP(CONCATENATE(_xlfn.XLOOKUP(C4, Productos!A:A, Productos!R:R, 0, 0, -1)," ",_xlfn.XLOOKUP(C4, Productos!A:A, Productos!S:S, 0, 0, -1)),'convinaciones fina'!B:B,'convinaciones fina'!H:H,"REVISAR")))) -> Consumax Sin Desc Afiliado, sin int hasta 6 cuotas | G18: =ROUND(IF(IFERROR(SEARCH("hasta 3", F18, 1), FALSE()), SUMIFS(Productos!G:G, Productos!A:A, $C$4, Productos!AD:AD, "<" & TODAY()+1, Productos!AE:AE, ">" & TODAY()-1)/3, IF(IFERROR(SEARCH("hasta 6", F18, 1), FALSE()), SUMIFS(Productos!G:G, Productos!A:A, $C$4, Productos!AD:AD, "<" & TODAY()+1, Productos!AE:AE, ">" & TODAY()-1)/6, IF(IFERROR(SEARCH("hasta 10", F18, 1), FALSE()), SUMIFS(Productos!G:G, Productos!A:A, $C$4, Productos!AD:AD, "<" & TODAY()+1, Productos!AE:AE, ">" & TODAY()-1)/10, IF(IFERROR(SEARCH("hasta 12", F18, 1), FALSE()), SUMIFS(Productos!G:G, Productos!A:A, $C$4, Productos!AD:AD, "<" & TODAY()+1, Productos!AE:AE, ">" & TODAY()-1)/12, IF(IFERROR(SEARCH("hasta 18", F18, 1), FALSE()), SUMIFS(Productos!G:G, Productos!A:A, $C$4, Productos!AD:AD, "<" & TODAY()+1, Productos!AE:AE, ">" & TODAY()-1)/18, IF(IFERROR(SEARCH("hasta 24", F18, 1), FALSE()), SUMIFS(Productos!G:G, Productos!A:A, $C$4, Productos!AD:AD, "<" & TODAY()+1, Productos!AE:AE, ">" & TODAY()-1)/24, IF(IFERROR(SEARCH("hasta 1 ", F18, 1), FALSE()), SUMIFS(Productos!G:G, Productos!A:A, $C$4, Productos!AD:AD, "<" & TODAY()+1, Productos!AE:AE, ">" & TODAY()-1),0))))))), 2) -> 11224.83 | H18: =+IF(G18>1, ROUNDUP(G18*0.95,1), "") -> 10663.6
F19: =IF(F8="Estas Ofertas ya no están en Vigencia","_", IF(IFERROR(SEARCH("Prove", L2,1), 0)>0, "Política comercial vigente","Prestamo DNI, "&_xlfn.XLOOKUP(CONCATENATE(_xlfn.XLOOKUP(C4, Productos!A:A, Productos!R:R, 0, 0, -1)," ",_xlfn.XLOOKUP(C4, Productos!A:A, Productos!S:S, 0, 0, -1)),'convinaciones fina'!B:B,'convinaciones fina'!I:I,"REVISAR"))) -> Prestamo DNI, hasta 4 cuotas "Sin interés" | H19: =+IF(G19>1, ROUNDUP(G19*0.95,1), "")
D21: Comentario: >>>>> | F21: =IF(G11>0.13,"Para creditos personales Previsora/Directo/Yolo se aplica +tiempo+beneficio.",IF(IFERROR(SEARCH("Prove", L2,1), 0)>0, "Puede aplicar Promo Bancaria o Mas tiempo Mas Beneficio (No ambos juntos)", IF(_xlfn.XLOOKUP($C$4, Productos!A:A, Productos!I:I, 0, 0, -1)="NO", "NO Tiene Descuento 5% si es Afiliado", IF(F8="Estas Ofertas ya no están en Vigencia", "_", IF(ISERROR(G8), "", CONCATENATE(" Tiene Descuento ", _xlfn.XLOOKUP($C$4, Productos!A:A, Productos!I:I, 0, 0, -1)*100, "% si es Afiliado")))))) -> Para creditos personales Previsora/Directo/Yolo se aplica +tiempo+beneficio.
F22: =IF(IFERROR(SEARCH("Prove", L2,1), 0)>0, "La política comercial es la de productos normales de salón.", IF(IFERROR(SEARCH("Tarj Bancaria, sin int hasta 3", F13, 1), 0)+IFERROR(SEARCH("Tarj Bancaria, sin int hasta 6", F13, 1), 0)+IFERROR(SEARCH("Tarj Bancaria, sin int hasta 9", F13, 1), 0)+IFERROR(SEARCH("Tarj Bancaria, sin int hasta 1", F13, 1), 0)>0, "Se puede reemplazar la oferta por promoción bancaria", "No Se vende con promociones Bancarias al precio Oferta, se puede hacerlo al precio lista")) -> No Se vende con promociones Bancarias al precio Oferta, se puede hacerlo al precio lista
F23: =IF(F8="Estas Ofertas ya no están en Vigencia","El plazo de esta oferta ya no está vigente",IF(ISBLANK(C4),"",IF(IFERROR(SEARCH("NO tiene",F11,1),FALSE()),"Todas las Financiaciones NO MENCIONADAS con Interés.","Resto de las Financiaciones CON INTERÉS"))) -> Resto de las Financiaciones CON INTERÉS
